verilog/verilog/bcd2binary.v
module bcd_to_binary(
    input [3:0] bcd,
    output reg [3:0] binary
);

    always @(*) begin
        if (bcd<= 4'd9)
            binary = bcd;
        else 
            binary = 4'bxxxx;
    end

endmodule

verilog/verilog/bcd2binary_tb.v
module bcd_to_binary_tb();

    reg [3:0] bcd;
    wire [3:0] binary;

    bcd_to_binary uut (
        .bcd(bcd),
        .binary(binary)
    );
    
    initial begin
        
        $dumpfile("bcd_to_binary.vcd");
        $dumpvars(0,bcd_to_binary_tb);

        $display("-----------------------------------------------------------------");
        $display("Time | BCD | Binary");
        $display("-----------------------------------------------------------------");

        $monitor("%0t | %b | %b", $time , bcd , binary);

        for (integer i = 0 ; i < 16 ; i = i+1) begin
            #10;
            bcd = i;
        end

        $display("------------------------------------------------------------------");
        $finish;
    end

endmodule

verilog/verilog/bcd_to_binary.vcd
$date
	Tue Sep 23 02:15:39 2025
$end
$version
	Icarus Verilog
$end
$timescale
	1s
$end
$scope module bcd_to_binary_tb $end
$var wire 4 ! binary [3:0] $end
$var reg 4 " bcd [3:0] $end
$scope module uut $end
$var wire 4 # bcd [3:0] $end
$var reg 4 $ binary [3:0] $end
$upscope $end
$scope begin $ivl_for_loop0 $end
$var integer 32 % i [31:0] $end
$upscope $end
$upscope $end
$enddefinitions $end
$comment Show the parameter values. $end
$dumpall
$end
#0
$dumpvars
b0 %
bx $
bx #
bx "
bx !
$end
#10
b0 !
b0 $
b1 %
b0 "
b0 #
#20
b1 !
b1 $
b10 %
b1 "
b1 #
#30
b10 !
b10 $
b11 %
b10 "
b10 #
#40
b11 !
b11 $
b100 %
b11 "
b11 #
#50
b100 !
b100 $
b101 %
b100 "
b100 #
#60
b101 !
b101 $
b110 %
b101 "
b101 #
#70
b110 !
b110 $
b111 %
b110 "
b110 #
#80
b111 !
b111 $
b1000 %
b111 "
b111 #
#90
b1000 !
b1000 $
b1001 %
b1000 "
b1000 #
#100
b1001 !
b1001 $
b1010 %
b1001 "
b1001 #
#110
bx !
bx $
b1011 %
b1010 "
b1010 #
#120
b1100 %
b1011 "
b1011 #
#130
b1101 %
b1100 "
b1100 #
#140
b1110 %
b1101 "
b1101 #
#150
b1111 %
b1110 "
b1110 #
#160
b10000 %
b1111 "
b1111 #
