verilog/verilog/btg.v
module binary_to_gray_4bit(
    input [3:0] binary,
    output [3:0] gray
);

    assign gray[3] = binary[3];
    assign gray[2] = binary[3] ^ binary[2];
    assign gray[1] = binary[2] ^ binary[1];
    assign gray[0] = binary[1] ^ binary[0];


endmodule

verilog/verilog/btg_tb.v
`timescale 1ps/1ps

module binary_to_gray_tb();
    reg [3:0] binary;

    wire [3:0] gray;

    // instantiate
    binary_to_gray_4bit uut (
        .binary(binary),
        .gray(gray)
    );

    initial begin
        $dumpfile("binary_to_gray.vcd");
        $dumpvars(0,binary_to_gray_tb);

        $display("-----------------------------------------------------");
        $display("Time | binary | Gray Code");
        $display("-----------------------------------------------------");

        // monitering changes
        $monitor("%0t | %b | %b" , $time , binary , gray);

        // test all possible\

        for (integer i = 0;i < 16 ; i = i +1) begin
            #10;
            binary = i;
        end

        $display("----------------------------------------------------");
        $finish;


    end

endmodule

verilog/verilog/binary_to_gray.vcd
$date
	Mon Sep 22 23:30:56 2025
$end
$version
	Icarus Verilog
$end
$timescale
	1ps
$end
$scope module binary_to_gray_tb $end
$var wire 4 ! gray [3:0] $end
$var reg 4 " binary [3:0] $end
$scope module uut $end
$var wire 4 # binary [3:0] $end
$var wire 4 $ gray [3:0] $end
$upscope $end
$scope begin $ivl_for_loop0 $end
$var integer 32 % i [31:0] $end
$upscope $end
$upscope $end
$enddefinitions $end
$comment Show the parameter values. $end
$dumpall
$end
#0
$dumpvars
b0 %
bx $
bx #
bx "
bx !
$end
#10
b0 !
b0 $
b1 %
b0 "
b0 #
#20
b1 !
b1 $
b10 %
b1 "
b1 #
#30
b11 !
b11 $
b11 %
b10 "
b10 #
#40
b10 !
b10 $
b100 %
b11 "
b11 #
#50
b110 !
b110 $
b101 %
b100 "
b100 #
#60
b111 !
b111 $
b110 %
b101 "
b101 #
#70
b101 !
b101 $
b111 %
b110 "
b110 #
#80
b100 !
b100 $
b1000 %
b111 "
b111 #
#90
b1100 !
b1100 $
b1001 %
b1000 "
b1000 #
#100
b1101 !
b1101 $
b1010 %
b1001 "
b1001 #
#110
b1111 !
b1111 $
b1011 %
b1010 "
b1010 #
#120
b1110 !
b1110 $
b1100 %
b1011 "
b1011 #
#130
b1010 !
b1010 $
b1101 %
b1100 "
b1100 #
#140
b1011 !
b1011 $
b1110 %
b1101 "
b1101 #
#150
b1001 !
b1001 $
b1111 %
b1110 "
b1110 #
#160
b1000 !
b1000 $
b10000 %
b1111 "
b1111 #
