verilog/verilog/simp1.v
module circ1_behav(
    input a,b,c,
    output reg f_original , f_simplified
);

    always @(*) begin
        f_original = (~a & b & c) | (a & b & ~c) | (a & b & c) | (~a & ~b & ~c);
        f_simplified = (b & c) | (~a & ~b & ~c);
        
    end


endmodule

verilog/verilog/simp1_tb.v

`timescale 1ps/1ps

module circ1_behav_tb;

    reg a,b,c;
    wire f_original,f_simplified;

    circ1_behav uut(
        .a(a),
        .b(b),
        .c(c),
        .f_original(f_original),
        .f_simplified(f_simplified)
    );

    initial begin
        $dumpfile("circ1behav.vcd");
        $dumpvars(0,circ1_behav_tb);

        $display("----------------------------------------------------------");
        $display("Time | a | b | c | f_original | f_simplified");
        $display("----------------------------------------------------------");

        $monitor("%0t  | %b | %b | %b |   %b   |   %b  ", $time,a,b,c,f_original,f_simplified);

        for (integer i = 0 ; i < 8 ; i = i+1) begin
            {a,b,c} = i;
            #10;
        end

        $display("-------------------------------------------------------------");
        $finish;
    end


endmodule

verilog/verilog/circ1behav.vcd
$date
	Tue Sep 23 10:26:11 2025
$end
$version
	Icarus Verilog
$end
$timescale
	1ps
$end
$scope module circ1_behav_tb $end
$var wire 1 ! f_simplified $end
$var wire 1 " f_original $end
$var reg 1 # a $end
$var reg 1 $ b $end
$var reg 1 % c $end
$scope module uut $end
$var wire 1 # a $end
$var wire 1 $ b $end
$var wire 1 % c $end
$var reg 1 " f_original $end
$var reg 1 ! f_simplified $end
$upscope $end
$scope begin $ivl_for_loop0 $end
$var integer 32 & i [31:0] $end
$upscope $end
$upscope $end
$enddefinitions $end
$comment Show the parameter values. $end
$dumpall
$end
#0
$dumpvars
b0 &
0%
0$
0#
1"
1!
$end
#10
0!
0"
1%
b1 &
#20
1$
0%
b10 &
#30
1!
1"
1%
b11 &
#40
0!
0"
1#
0$
0%
b100 &
#50
1%
b101 &
#60
1"
1$
0%
b110 &
#70
1!
1%
b111 &
#80
b1000 &
