verilog/verilog/xs3tobcd.v
module excess3_to_bcd(
    input [3:0] excess3,
    output [3:0] bcd
);

    assign bcd = excess3 - 4'd3;
    

endmodule

verilog/verilog/xs3tobcd_tb.v
module excess3_to_bcd_tb();

    reg [3:0] excess3;
    wire [3:0] bcd;

    excess3_to_bcd uut (
        .excess3(excess3),
        .bcd(bcd)
    );
    initial begin
        $dumpfile("excess3_to_bcd.vcd");
        $dumpvars(0,excess3_to_bcd_tb);

        $display("------------------------------------------");
        $display("Time | excess3 | BCD");
        $display("------------------------------------------");

        $monitor("%0t | %b | %b" , $time , excess3 , bcd);

        for (integer i = 3 ; i <= 12 ; i = i+1) begin
            #10
            excess3 = i;
        end


        $display("------------------------------------------");
        $finish;
    end

endmodule

verilog/verilog/excess3_to_bcd.vcd
$date
	Tue Sep 23 01:47:16 2025
$end
$version
	Icarus Verilog
$end
$timescale
	1s
$end
$scope module excess3_to_bcd_tb $end
$var wire 4 ! bcd [3:0] $end
$var reg 4 " excess3 [3:0] $end
$scope module uut $end
$var wire 4 # excess3 [3:0] $end
$var wire 4 $ bcd [3:0] $end
$upscope $end
$scope begin $ivl_for_loop0 $end
$var integer 32 % i [31:0] $end
$upscope $end
$upscope $end
$enddefinitions $end
$comment Show the parameter values. $end
$dumpall
$end
#0
$dumpvars
b11 %
bx $
bx #
bx "
bx !
$end
#10
b100 %
b0 !
b0 $
b11 "
b11 #
#20
b101 %
b1 !
b1 $
b100 "
b100 #
#30
b110 %
b10 !
b10 $
b101 "
b101 #
#40
b111 %
b11 !
b11 $
b110 "
b110 #
#50
b1000 %
b100 !
b100 $
b111 "
b111 #
#60
b1001 %
b101 !
b101 $
b1000 "
b1000 #
#70
b1010 %
b110 !
b110 $
b1001 "
b1001 #
#80
b1011 %
b111 !
b111 $
b1010 "
b1010 #
#90
b1100 %
b1000 !
b1000 $
b1011 "
b1011 #
#100
b1101 %
b1001 !
b1001 $
b1100 "
b1100 #
