verilog/verilog/full_adder.v
module full_adder_gate(
 	input a, b ,cin,
 	output sum , cout
);

 	wire s1,c1,c2;

 	xor x1(s1,a,b);
 	xor x2(sum,s1,cin);
 	and a1(c1,a,b);
 	and a2(c2,s1,cin);
 	or o1(cout,c1,c2);

endmodule

verilog/verilog/full_adder_tb.v
`timescale 1ps/1ps

module fulle_adder_tb();

    reg a , b ,cin ;
    wire sum, cout;


    full_adder_gate uut(
        .a(a),
        .b(b),
        .cin(cin),
        .sum(sum),
        .cout(cout)
    );

    initial begin
        $dumpfile("full_adder.vcd");
        $dumpvars(0,fulle_adder_tb);

        $display("------------------------------------");
        $display("Time | a | b | cin | sum | cout");
        $display("------------------------------------");

        $monitor("%0t | %b | %b | %b | %b | %b", $time, a,b,cin ,sum , cout);

        a = 1'b0; b = 1'b0; cin = 1'b0;
        #10;

        // a=0, b=0, cin=1
        a = 1'b0; b = 1'b0; cin = 1'b1;
        #10;

        // a=0, b=1, cin=0
        a = 1'b0; b = 1'b1; cin = 1'b0;
        #10;

        // a=0, b=1, cin=1
        a = 1'b0; b = 1'b1; cin = 1'b1;
        #10;

        // a=1, b=0, cin=0
        a = 1'b1; b = 1'b0; cin = 1'b0;
        #10;

        // a=1, b=0, cin=1
        a = 1'b1; b = 1'b0; cin = 1'b1;
        #10;

        // a=1, b=1, cin=0
        a = 1'b1; b = 1'b1; cin = 1'b0;
        #10;

        // a=1, b=1, cin=1
        a = 1'b1; b = 1'b1; cin = 1'b1;
        #10;
        
        $display("---------------------------------------");
        $finish;

    end

endmodule

verilog/verilog/full_adder.vcd
$date
	Sun Sep 21 19:41:09 2025
$end
$version
	Icarus Verilog
$end
$timescale
	1ps
$end
$scope module fulle_adder_tb $end
$var wire 1 ! sum $end
$var wire 1 " cout $end
$var reg 1 # a $end
$var reg 1 $ b $end
$var reg 1 % cin $end
$scope module uut $end
$var wire 1 # a $end
$var wire 1 $ b $end
$var wire 1 & c1 $end
$var wire 1 ' c2 $end
$var wire 1 % cin $end
$var wire 1 " cout $end
$var wire 1 ( s1 $end
$var wire 1 ! sum $end
$upscope $end
$upscope $end
$enddefinitions $end
$comment Show the parameter values. $end
$dumpall
$end
#0
$dumpvars
0(
0'
0&
0%
0$
0#
0"
0!
$end
#10
1!
1%
#20
1(
0%
1$
#30
1"
0!
1'
1%
#40
0"
1!
0'
0%
0$
1#
#50
1"
0!
1'
1%
#60
0'
0(
1&
0%
1$
#70
1!
1%
